flask_query_builder/__init__.py
flask_query_builder/exceptions.py
flask_query_builder/filters.py
flask_query_builder/querying.py
flask_query_builder/sorts.py
flask_query_builder-0.3.5.dist-info/LICENSE
flask_query_builder-0.3.5.dist-info/METADATA
flask_query_builder-0.3.5.dist-info/WHEEL
flask_query_builder-0.3.5.dist-info/RECORD
